rowantree/auth/service/contracts/__init__.py
rowantree/auth/service/contracts/duplicate_key_error.py
rowantree/auth/service/contracts/exceeded_retry_count_error.py
rowantree/auth/service/controllers/__init__.py
rowantree/auth/service/controllers/abstract_controller.py
rowantree/auth/service/controllers/register.py
rowantree/auth/service/controllers/token.py
rowantree/auth/service/handlers/__init__.py
rowantree/auth/service/handlers/main.py
rowantree/auth/service/services/__init__.py
rowantree/auth/service/services/abstract_service.py
rowantree/auth/service/services/auth.py
rowantree/auth/service/services/db/__init__.py
rowantree/auth/service/services/db/dao.py
rowantree/auth/service/services/db/incorrect_row_count_error.py
rowantree/auth/service/services/db/utils.py
rowantree.auth.service-0.13.0.dist-info/LICENSE
rowantree.auth.service-0.13.0.dist-info/METADATA
rowantree.auth.service-0.13.0.dist-info/WHEEL
rowantree.auth.service-0.13.0.dist-info/top_level.txt
rowantree.auth.service-0.13.0.dist-info/RECORD
