Metadata-Version: 2.1
Name: rowantree.auth.service
Version: 0.13.0
Summary: The Rowan Tree Authentication and Authorization Service
Author: Joshua C. Burt
Author-email: joshburt@shapeandshare.com
License: MIT
Requires-Python: >=3.9
License-File: LICENSE
Requires-Dist: uvicorn[standard] (~=0.18)
Requires-Dist: fastapi (~=0.81)
Requires-Dist: mysql-connector-python (~=8.0)
Requires-Dist: starlette (~=0.19)
Requires-Dist: pydantic (~=1.10)
Requires-Dist: python-multipart (>=0.0.5)
Requires-Dist: rowantree.contracts (~=0.16)
Requires-Dist: rowantree.common.sdk (~=0.4)
Requires-Dist: rowantree.auth.sdk (~=0.16)
